bitstillery_pyi18next/__init__.py
bitstillery_pyi18next/functions.py
bitstillery_pyi18next/i18next.py
bitstillery_pyi18next/translate.py
bitstillery_pyi18next/utility.py
bitstillery_pyi18next/backends/__init__.py
bitstillery_pyi18next/backends/fs.py
bitstillery_pyi18next/loaders/__init__.py
bitstillery_pyi18next-0.0.7.dist-info/METADATA
bitstillery_pyi18next-0.0.7.dist-info/WHEEL
bitstillery_pyi18next-0.0.7.dist-info/licenses/LICENSE
bitstillery_pyi18next-0.0.7.dist-info/RECORD
